z3gi/__init__.py
z3gi/__main__.py
z3gi/sample.py
z3gi/encoders/__init__.py
z3gi/encoders/expressive.py
z3gi/encoders/interface.py
z3gi/encoders/mealy.py
z3gi/encoders/natural.py
z3gi/encoders/propositional.py
z3gi/parsers/__init__.py
z3gi/parsers/abbadingo.py
z3gi-0.1.1.dist-info/DESCRIPTION.rst
z3gi-0.1.1.dist-info/METADATA
z3gi-0.1.1.dist-info/RECORD
z3gi-0.1.1.dist-info/WHEEL
z3gi-0.1.1.dist-info/metadata.json
z3gi-0.1.1.dist-info/top_level.txt
