Metadata-Version: 2.0
Name: z3gi
Version: 0.1.1
Summary: Grammatical inference using the Z3 SMT solver
Home-page: https://gitlab.science.ru.nl/rick/z3gi
Author: Rick Smetsers
Author-email: ricksmet@gmail.com
License: MIT
Platform: UNKNOWN
Classifier: Development Status :: 3 - Alpha
Classifier: Environment :: Console
Classifier: Intended Audience :: Science/Research
Classifier: License :: OSI Approved :: MIT License
Classifier: Operating System :: OS Independent
Classifier: Programming Language :: Python
Classifier: Programming Language :: Python :: 2.7
Classifier: Programming Language :: Python :: 3
Classifier: Topic :: Scientific/Engineering :: Artificial Intelligence
Requires-Dist: z3-solver
